pyvetic/__init__.py
pyvetic/constants.py
pyvetic/logger.py
pyvetic/utils.py
pyvetic/django/__init__.py
pyvetic/django/middleware/__init__.py
pyvetic/django/middleware/exception.py
pyvetic/django/middleware/prometheus.py
pyvetic/fastapi/__init__.py
pyvetic/fastapi/middleware/__init__.py
pyvetic/fastapi/middleware/exception.py
pyvetic/fastapi/middleware/prometheus.py
pyvetic/instrument/__init__.py
pyvetic/instrument/prometheus.py
pyvetic-0.34.0.dist-info/METADATA
pyvetic-0.34.0.dist-info/WHEEL
pyvetic-0.34.0.dist-info/top_level.txt
pyvetic-0.34.0.dist-info/RECORD
