Metadata-Version: 2.4
Name: pyvetic
Version: 0.34.0
Summary: Internal package for common utils
Home-page: https://github.com/vetic-in/pyvetic
Author: Vetic
Author-email: techadmin@vetic.in
Classifier: Programming Language :: Python :: 3
Classifier: Operating System :: OS Independent
Classifier: Intended Audience :: Developers
Requires-Python: >=3.8,<3.13
Requires-Dist: python-logging-loki>=0.3.0
Requires-Dist: prometheus_client>=0.20.0
Requires-Dist: psutil>=7.0.0
Provides-Extra: fastapi
Requires-Dist: fastapi>=0.90.0; extra == "fastapi"
Requires-Dist: uvicorn; extra == "fastapi"
Provides-Extra: django
Requires-Dist: Django>=3.2; extra == "django"
Dynamic: author
Dynamic: author-email
Dynamic: classifier
Dynamic: description
Dynamic: description-content-type
Dynamic: home-page
Dynamic: provides-extra
Dynamic: requires-dist
Dynamic: requires-python
Dynamic: summary
